encapsia_api/__init__.py
encapsia_api/analytics.py
encapsia_api/credentials.py
encapsia_api/lib.py
encapsia_api/package.py
encapsia_api/plugin.py
encapsia_api/py.typed
encapsia_api/resilient_request.py
encapsia_api/rest.py
encapsia_api/tests/__init__.py
encapsia_api/tests/test_credentials.py
encapsia_api/tests/test_package.py
encapsia_api/tests/test_plugin.py
encapsia_api/tests/test_resilient_request.py
encapsia_api/tests/test_rest.py
encapsia_api/util.py
encapsia_api-0.4.8.dist-info/LICENSE
encapsia_api-0.4.8.dist-info/METADATA
encapsia_api-0.4.8.dist-info/WHEEL
encapsia_api-0.4.8.dist-info/RECORD
