Metadata-Version: 2.1
Name: encapsia-api
Version: 0.4.8
Summary: Client API for talking to an Encapsia system.
Home-page: https://github.com/Encapsia/encapsia-api
License: MIT
Keywords: encapsia,eSource,EDC,Clinical Trials
Author: Timothy Corbett-Clark
Author-email: timothy.corbettclark@gmail.com
Maintainer: Petre Mierluțiu
Maintainer-email: petre.mierlutiu@aixial.com
Requires-Python: >=3.8,<4.0
Classifier: License :: OSI Approved :: MIT License
Classifier: Programming Language :: Python :: 3
Classifier: Programming Language :: Python :: 3.8
Classifier: Programming Language :: Python :: 3.9
Classifier: Programming Language :: Python :: 3.10
Classifier: Programming Language :: Python :: 3.11
Classifier: Programming Language :: Python :: 3.12
Requires-Dist: arrow (>=1.2.0)
Requires-Dist: requests[security] (>=2.24)
Requires-Dist: toml (>=0.10)
